{
  "slug": "gioi-tu-3",
  "title": "Giới từ (3) — Tính từ đi với giới từ",
  "level": "B1",
  "topic": "prepositions",
  "summary": "Tổng hợp các cụm Adj + Preposition thường gặp: Adj + to, of, for, at, with, in, from, about, on.",
  "sections": [
    {
      "title": "Adj + to / Adj + of",
      "body": "## Tính từ đi với giới từ (Phần 1)\n\n### Adj + to\n\n| Cụm từ | Nghĩa | Ví dụ |\n|---|---|---|\n| **acceptable to** | có thể chấp nhận | *Is this proposal acceptable to you?* |\n| **accustomed to** | quen với (thường dùng get/be accustomed to) | *I soon got accustomed to his strange ways.* |\n| **agreeable to** | có thể đồng ý, thích hợp với | *He said the terms were not agreeable to him.* |\n| **applicable to** | có thể ứng dụng | *The results of experiments on animals will be applicable to human beings.* |\n| **appropriate to** | thích hợp | *It's necessary for the homicide to incur a punishment appropriate to his cruelties.* |\n| **addicted to** | say mê cái gì, nghiện | *Children are often addicted to fairy stories.* |\n| **bad to** | có hại cho, không tốt cho | *Staying up late is bad to us.* |\n| **contrary to** | trái với | *Contrary to his expectations, he found the atmosphere exciting.* |\n| **clear to** | rõ ràng | *You could see clear to the bottom of the lagoon.* |\n| **close to** | gần | *He spent close to 30 years in jail.* |\n| **dedicated/devoted to** | hiến dâng, tận tụy | *I am dedicated to making this world a better place. / She is devoted to her job.* |\n| **engaged to** | đính hôn với | *She was engaged to a lecturer.* |\n| **equal to** | đủ sức, đủ khả năng gánh vác | *I just don't feel equal to the challenge that I'm facing now.* |\n| **essential to/for** | cần thiết | *Food is essential to/for life.* |\n| **harmful to** | có hại | *Smoking is harmful to health.* |\n| **faithful/loyal to** | trung thành | *He remained faithful to the ideals of the party. / These brave soldiers are always loyal to their ideal.* |\n| **grateful/thankful to sb for st** | biết ơn ai về điều gì | *I'm grateful/thankful to you for all your help.* |\n| **important to sb** | quan trọng đối với ai | *It's important to me that you should be there.* |\n| **indifferent to** | thờ ơ, lãnh đạm | *The government cannot afford to be indifferent to public opinion.* |\n| **kind to sb** | tử tế với ai | *He was very kind to me when the children were ill.* |\n| **likely to** | có khả năng, có thể thích hợp | *He is not likely to come now.* |\n| **married to** | kết hôn với | *Ali is married to Salma.* |\n| **necessary to** | cần thiết, thiết yếu | *Sleeping is necessary to health.* |\n| **open to** | cởi mở | *The system is open to abuse.* |\n| **opposed to** | bất đồng, phản đối | *He was bitterly opposed to the war.* |\n| **polite to** | lịch sự với ai | *You must be more polite to the customers.* |\n| **related to** | liên quan đến | *He was related to that crime.* |\n| **responsible to sb** | chịu trách nhiệm trước ai | *The head of state is responsible to his people and must obey the law.* |\n| **similar to** | tương tự | *Your hat is similar to mine.* |\n| **sensitive to/about** | nhạy cảm | *She is very sensitive to other people's feelings.* |\n| **used to** | quen với | *I'm used to getting up early.* |\n\n### Adj + of\n\n| Cụm từ | Nghĩa | Ví dụ |\n|---|---|---|\n| **afraid of** | sợ hãi | *Are you afraid of snakes?* |\n| **ashamed of** | xấu hổ, bối rối về | *She was deeply ashamed of her behaviour at the party.* |\n| **aware of** | nhận thức về cái gì | *He was well aware of the problem. (Trái nghĩa: unaware of)* |\n| **capable of** | có khả năng làm gì | *He is capable of anything if it furthers his ambition.* |\n| **careful of/with/about** | cẩn thận | *He was very careful of his reputation.* |\n| **certain of/about** | chắc chắn về | *You don't seem too certain of it.* |\n| **characteristic of** | đặc trưng cho tính cách ai/vật gì | *Enthusiasm is characteristic of him.* |\n| **conscious of** | nhận thức, chú ý đến | *She's very conscious of the problems involved.* |\n| **desirous of** | khao khát | *The Pope was desirous of peace in Europe.* |\n| **doubtful of/about** | nghi ngờ | *I was doubtful of my judgement.* |\n| **envious/jealous of** | ghen tị | *He was envious of the local boys. / Other girls were jealous of her good looks.* |\n| **fond of** | ưa thích, thích | *I'm fond of cooking.* |\n| **frightened of** | sợ hãi | *I've always been frightened of snakes.* |\n| **full of** | đầy | *The bin is full of rubbish.* |\n| **guilty of** | có tội, cảm thấy có lỗi | *She was guilty of a serious error of judgement.* |\n| **hopeful of/about** | hy vọng | *She is hopeful of returning to work soon.* |\n| **incapable of** | không có khả năng | *Professors who seem incapable of any original thought.* |\n| **innocent of** | vô tội, ngây thơ | *She was found innocent of any crime.* |\n| **independent of** | độc lập, không lệ thuộc | *The study is totally independent of central government.* |\n| **nervous of/about** | lo lắng | *He's always been a little nervous of speaking in public.* |\n| **proud of** | tự hào về | *They are proud of their daughter.* |\n| **respectful of/for** | lễ phép, tôn trọng | *I'm respectful of your opinion.* |\n| **be/get rid of** | tống khứ, loại bỏ | *We got rid of all the old furniture.* |\n| **sick of** | chán ngấy | *I'm sick of waiting around like this.* |\n| **scared of** | sợ hãi | *All small children are scared of ghosts.* |\n| **sure of** | chắc chắn | *I'm not sure of the results.* |\n| **suspicious of/about** | nghi ngờ | *He was suspicious of/about her motives.* |\n| **tired of** | mệt mỏi, chán vì việc gì | *I am tired of studying all the time.* |\n| **terrified of** | khiếp sợ | *I'm terrified of spiders.* |\n| **typical of** | điển hình | *This meal is typical of local cookery.* |\n| **unaware of** | không nhận thức được | *He was unaware of my presence.* |\n\n"
    },
    {
      "title": "Adj + for / Adj + at / Adj + with",
      "body": "## Tính từ đi với giới từ (Phần 2)\n\n### Adj + for\n\n| Cụm từ | Nghĩa | Ví dụ |\n|---|---|---|\n| **anxious for sb about st** | lo lắng cho ai về điều gì | *Parents are naturally anxious for their children.* |\n| **appreciated for** | được đánh giá cao vì | *I was appreciated for my help.* |\n| **available for** | có sẵn, sẵn sàng cho | *The Prime Minister was not available for comment.* |\n| **bad for** | có hại cho | *Staying up late is bad for our health.* |\n| **convenient for** | thuận tiện cho | *Will it be convenient for you to start work tomorrow?* |\n| **difficult for** | khó khăn đối với | *The questions are too difficult for the children.* |\n| **eager for** | hào hứng, khao khát | *I am eager for my next trip.* |\n| **eligible for** | đủ điều kiện cho | *Only those over 70 are eligible for the special payment.* |\n| **enough for** | đủ cho | *Have we got enough sandwiches for lunch?* |\n| **important for** | quan trọng cho | *Oxygen is important for our lives.* |\n| **famous for** | nổi tiếng vì | *Hanoi is famous for 'pho'.* |\n| **grateful/thankful for st** | biết ơn vì điều gì | *I was grateful for the light so I could see.* |\n| **late for** | trễ, muộn | *He was ten minutes late for school.* |\n| **necessary for** | cần thiết cho | *She hasn't the experience necessary for the job.* |\n| **perfect for** | hoàn hảo cho | *This dress would be perfect for my date.* |\n| **prepared for st** | sẵn sàng, chuẩn bị cho | *The troops were being prepared for battle.* |\n| **qualified for** | đủ khả năng, điều kiện | *He is qualified for this dangerous mission.* |\n| **responsible for st/V-ing** | chịu trách nhiệm về | *You must be responsible for paying these bills.* |\n| **ready for** | sẵn sàng cho | *I'm ready for the exam.* |\n| **sorry for** | lấy làm tiếc, hối hận vì | *Aren't you sorry for what you've done?* |\n| **suitable for** | thích hợp cho | *This programme is not suitable for children.* |\n| **sufficient for** | đầy đủ cho nhu cầu | *A small income which was sufficient for her needs.* |\n\n### Adj + at\n\n| Cụm từ | Nghĩa | Ví dụ |\n|---|---|---|\n| **amazed/astonished at/by** | ngạc nhiên vì | *My parents looked astonished at my news.* |\n| **amused at/by** | thích thú, buồn cười vì | *Everyone is amused at/by the clown's gestures.* |\n| **angry at/about st** | tức giận về việc gì | *I was very angry at how rainy it was.* |\n| **annoyed at/about st** | bực mình vì cái gì | *He was annoyed at my carelessness.* |\n| **bad at** | dốt, tệ về môn gì | *I'm bad at Maths.* |\n| **clever at** | thông minh, khéo léo về | *She's clever at getting what she wants.* |\n| **delighted at/by/with** | vui vẻ, hài lòng về | *She was delighted by/at the news of the wedding.* |\n| **excellent at** | xuất sắc về | *My teacher is excellent at English.* |\n| **furious at** | giận dữ về việc gì | *They were furious at not being invited.* |\n| **good at** | giỏi về | *I'm good at English.* |\n| **hopeless at** | vô vọng, rất kém | *I'm hopeless at science.* |\n| **lucky at** | may mắn trong việc gì | *I'm lucky at winning this trip.* |\n| **proficient in/at** | thành thạo về | *I was proficient at my job.* |\n| **quick at** | nhanh nhạy trong việc gì | *He is quick at solving mathematical problems.* |\n| **slow at** | chậm chạp đưa ra quyết định/làm gì | *She is slow at making up her mind.* |\n| **shocked at/by** | sốc vì | *I was shocked at the news of her death.* |\n| **skillful at** | khéo léo, tài giỏi về | *He is skillful at inventing excuses.* |\n| **surprised at/by** | ngạc nhiên vì | *We were surprised at your behavior.* |\n\n### Adj + with\n\n| Cụm từ | Nghĩa | Ví dụ |\n|---|---|---|\n| **acquainted with** | quen với cái gì | *The students are already acquainted with the work of Shakespeare.* |\n| **associated with** | liên kết, cộng tác với | *He no longer wished to be associated with the party's policy.* |\n| **annoyed with sb at/about st** | khó chịu với ai về việc gì | *Kelly was annoyed with him.* |\n| **bored/fed up with** | chán ngấy | *I'm bored with my job. / I got fed up with his constant complaining.* |\n| **busy with** | bận rộn với | *They were busy with preparations for their wedding.* |\n| **content with** | bằng lòng, hài lòng với | *She seemed quite content with her results.* |\n| **careful with** | cẩn thận với | *Please be careful with my glasses.* |\n| **connected with** | kết nối, liên quan với | *The fall in sales is connected with the decline in employment.* |\n| **crowded/packed with** | đông đúc, đầy | *a room crowded with books.* |\n| **disappointed with/at/by/in** | thất vọng về/với | *I was very disappointed with myself. / I'm disappointed in you.* |\n| **dissatisfied with** | không hài lòng với | *He has been very dissatisfied with his life.* |\n| **delighted with** | vui sướng với | *I was delighted with my presents.* |\n| **familiar with** | quen thuộc, am hiểu | *He is familiar with me.* |\n| **friendly with** | thân thiện với | *I am very friendly with the people.* |\n| **generous with** | rộng rãi, hào phóng với | *To be generous with your time.* |\n| **gentle with** | ôn hòa, lịch thiệp với | *He is gentle with women and children.* |\n| **involved with** | liên quan, có quan hệ tình cảm với | *Angela told me she was involved with someone else.* |\n| **pleased with** | hài lòng với | *I'm very pleased with the results.* |\n| **patient with** | nhẫn nại với | *Susan's very patient with the children.* |\n| **popular with** | được yêu thích bởi (số đông) | *These policies are unlikely to prove popular with voters.* |\n| **satisfied with** | thỏa mãn, hài lòng với | *He felt satisfied with his job.* |\n| **troubled with** | bồn chồn, lo lắng về | *Don't be troubled with that.* |\n| **wrong with** | có vấn đề, sai sót với | *There's something wrong with the printer.* |\n\n"
    },
    {
      "title": "Adj + in / from / about / on",
      "body": "## Tính từ đi với giới từ (Phần 3)\n\n### Adj + in\n\n| Cụm từ | Nghĩa | Ví dụ |\n|---|---|---|\n| **experienced in** | có kinh nghiệm về | *He's very experienced in looking after animals.* |\n| **honest in** | trung thực trong việc gì | *Always be honest in whatever you do.* |\n| **involved in** | liên quan đến, tham gia vào | *We need to examine all the costs involved in the project. / I was so involved in my book...* |\n| **interested in** | quan tâm, hứng thú | *I'm interested in football.* |\n| **proficient in/at** | thành thạo | *She felt reasonably proficient in Italian.* |\n| **rich in** | giàu, chứa nhiều (chất dinh dưỡng...) | *Many vegetables and fruits are rich in vitamins.* |\n| **successful in** | thành công trong | *Finally, they were successful in putting out the fire.* |\n| **weak in** | yếu, kém về môn gì | *He is the student who is weak in algebra.* |\n\n### Adj + from\n\n| Cụm từ | Nghĩa | Ví dụ |\n|---|---|---|\n| **absent from** | vắng mặt ở | *Most pupils were absent from school at least once.* |\n| **derived from** | bắt nguồn từ | *The word 'fiction' is derived from the Greek 'fictus'.* |\n| **different from** | khác với | *Their tastes are different from mine.* |\n| **distinct from** | khác biệt hoàn toàn | *Man is distinct from animals.* |\n| **free of/from** | không chứa hoặc không bị ảnh hưởng bởi thứ xấu | *free from difficulty/doubt/fear / free from artificial colours.* |\n| **far from** | cách xa | *My house is far from my school.* |\n| **isolated/separate from** | tách biệt, cô lập khỏi | *He was isolated from all the other prisoners. / kept entirely separate from the other.* |\n\n### Adj + about\n\n| Cụm từ | Nghĩa | Ví dụ |\n|---|---|---|\n| **anxious about sth/for sb** | lo lắng về việc gì | *He seemed anxious about the meeting.* |\n| **confused about** | bối rối, nhầm lẫn về | *She was utterly confused about what had happened.* |\n| **careful about** | cẩn thận về | *I'm very careful about washing my hands before eating.* |\n| **concerned about** | băn khoăn, quan tâm về | *The President is deeply concerned about this issue.* |\n| **crazy about** | điên cuồng, cực kỳ thích | *It's pretty obvious he's crazy about you.* |\n| **certain about/of** | chắc chắn về | *You don't seem too certain about it.* |\n| **curious about** | tò mò, hiếu kỳ về | *She was curious about what had happened.* |\n| **doubtful about** | hoài nghi | *Rosy was doubtful about the whole idea.* |\n| **excited about** | hứng thú, phấn khích | *I'm very excited about the news.* |\n| **enthusiastic about** | nhiệt tình, hứng thú | *You don't sound very enthusiastic about the idea.* |\n| **glad about** | vui mừng về | *She wasn't going to leave, and he was glad about that.* |\n| **happy about/with** | hạnh phúc, hài lòng | *If there's anything you're not happy about, come and ask.* |\n| **hopeful of/about** | hy vọng về | *He is not very hopeful about the outcome of the interview.* |\n| **nervous of/about** | lo lắng về | *She was nervous about walking home so late.* |\n| **optimistic/pessimistic about** | lạc quan/bi quan về | *Peter is not optimistic about the outcome. / Doctors are pessimistic about his recovery.* |\n| **serious about** | nghiêm túc về | *I'm serious about my work.* |\n| **suspicious of/about** | nghi ngờ | *I'm always suspicious about his kindness.* |\n| **upset about** | buồn bã, thất vọng về | *I was upset about losing my money.* |\n| **worried about** | lo lắng về | *He is always worried about his wife.* |\n\n### Adj + on\n\n| Cụm từ | Nghĩa | Ví dụ |\n|---|---|---|\n| **based on** | dựa trên | *This novel is based on a real story.* |\n| **dependent on** | phụ thuộc vào | *Success is dependent on how hard you work.* |\n| **keen on** | thích thú | *The kids are mad keen on computer games.* |\n\n"
    }
  ],
  "exerciseSets": [
    {
      "id": "PREP-C1",
      "title": "Luyện Tập Giới Từ 6 (30 câu)",
      "exercises": [
        {
          "id": "290150",
          "kind": "mcq",
          "question": "Thank you for all your help. You’ve been very kind ……….. me",
          "options": [
            {
              "key": "A",
              "text": "of"
            },
            {
              "key": "B",
              "text": "to"
            },
            {
              "key": "C",
              "text": "at"
            },
            {
              "key": "D",
              "text": "for"
            }
          ],
          "answer": "B",
          "explanation": ""
        },
        {
          "id": "290151",
          "kind": "mcq",
          "question": "I don't think that I'm acquainted .......... him",
          "options": [
            {
              "key": "A",
              "text": "with"
            },
            {
              "key": "B",
              "text": "to"
            },
            {
              "key": "C",
              "text": "for"
            },
            {
              "key": "D",
              "text": "by"
            }
          ],
          "answer": "A",
          "explanation": ""
        },
        {
          "id": "290152",
          "kind": "mcq",
          "question": "What have I done wrong ? Why are you annoyed .... me?",
          "options": [
            {
              "key": "A",
              "text": "about"
            },
            {
              "key": "B",
              "text": "with"
            },
            {
              "key": "C",
              "text": "at"
            },
            {
              "key": "D",
              "text": "by"
            }
          ],
          "answer": "B",
          "explanation": ""
        },
        {
          "id": "290153",
          "kind": "mcq",
          "question": "Opening the parcel, he was surprised ……what he saw.",
          "options": [
            {
              "key": "A",
              "text": "at"
            },
            {
              "key": "B",
              "text": "in"
            },
            {
              "key": "C",
              "text": "on"
            },
            {
              "key": "D",
              "text": "of"
            }
          ],
          "answer": "A",
          "explanation": ""
        },
        {
          "id": "290154",
          "kind": "mcq",
          "question": "Rosy married a wealthy man. She got married ….him last June.",
          "options": [
            {
              "key": "A",
              "text": "by"
            },
            {
              "key": "B",
              "text": "for"
            },
            {
              "key": "C",
              "text": "about"
            },
            {
              "key": "D",
              "text": "to"
            }
          ],
          "answer": "D",
          "explanation": ""
        },
        {
          "id": "290155",
          "kind": "mcq",
          "question": "Don’t be familiar ………. John. He is a dishonest man.",
          "options": [
            {
              "key": "A",
              "text": "into"
            },
            {
              "key": "B",
              "text": "to"
            },
            {
              "key": "C",
              "text": "with"
            },
            {
              "key": "D",
              "text": "for"
            }
          ],
          "answer": "C",
          "explanation": ""
        },
        {
          "id": "290156",
          "kind": "mcq",
          "question": "My plan is similar …….yours, but it is different …… Ken’s",
          "options": [
            {
              "key": "A",
              "text": "to-to"
            },
            {
              "key": "B",
              "text": "from-to"
            },
            {
              "key": "C",
              "text": "to-from"
            },
            {
              "key": "D",
              "text": "from-from"
            }
          ],
          "answer": "C",
          "explanation": ""
        },
        {
          "id": "290157",
          "kind": "mcq",
          "question": "It was very nice .... you to do my shopping for me. Thank you very much",
          "options": [
            {
              "key": "A",
              "text": "of"
            },
            {
              "key": "B",
              "text": "for"
            },
            {
              "key": "C",
              "text": "to"
            },
            {
              "key": "D",
              "text": "with"
            }
          ],
          "answer": "A",
          "explanation": ""
        },
        {
          "id": "290158",
          "kind": "mcq",
          "question": "I’m capable ………….. speaking two languages",
          "options": [
            {
              "key": "A",
              "text": "to"
            },
            {
              "key": "B",
              "text": "with"
            },
            {
              "key": "C",
              "text": "for"
            },
            {
              "key": "D",
              "text": "of"
            }
          ],
          "answer": "D",
          "explanation": ""
        },
        {
          "id": "290159",
          "kind": "mcq",
          "question": "Contrary ………… his doctor’s orders, he has gone back to work",
          "options": [
            {
              "key": "A",
              "text": "from"
            },
            {
              "key": "B",
              "text": "to"
            },
            {
              "key": "C",
              "text": "with"
            },
            {
              "key": "D",
              "text": "by"
            }
          ],
          "answer": "B",
          "explanation": ""
        },
        {
          "id": "290160",
          "kind": "mcq",
          "question": "I‘ve been trying to learn Spanish but I’m not very satisfied .... my progress.",
          "options": [
            {
              "key": "A",
              "text": "to"
            },
            {
              "key": "B",
              "text": "with"
            },
            {
              "key": "C",
              "text": "at"
            },
            {
              "key": "D",
              "text": "by"
            }
          ],
          "answer": "B",
          "explanation": ""
        },
        {
          "id": "290161",
          "kind": "mcq",
          "question": "Attending all the lectures is important ……… us",
          "options": [
            {
              "key": "A",
              "text": "for"
            },
            {
              "key": "B",
              "text": "to"
            },
            {
              "key": "C",
              "text": "at"
            },
            {
              "key": "D",
              "text": "on"
            }
          ],
          "answer": "B",
          "explanation": ""
        },
        {
          "id": "290162",
          "kind": "mcq",
          "question": "The United States became independent …………… England in 1776.",
          "options": [
            {
              "key": "A",
              "text": "on"
            },
            {
              "key": "B",
              "text": "with"
            },
            {
              "key": "C",
              "text": "of"
            },
            {
              "key": "D",
              "text": "to"
            }
          ],
          "answer": "C",
          "explanation": ""
        },
        {
          "id": "290163",
          "kind": "mcq",
          "question": "We were grateful……….. our friends ………. all the assistance",
          "options": [
            {
              "key": "A",
              "text": "to-with"
            },
            {
              "key": "B",
              "text": "for-to"
            },
            {
              "key": "C",
              "text": "to-for"
            },
            {
              "key": "D",
              "text": "for-with"
            }
          ],
          "answer": "C",
          "explanation": ""
        },
        {
          "id": "290164",
          "kind": "mcq",
          "question": "You know that stealing is wrong! You should feel ashamed ………… yourself!",
          "options": [
            {
              "key": "A",
              "text": "with"
            },
            {
              "key": "B",
              "text": "on"
            },
            {
              "key": "C",
              "text": "of"
            },
            {
              "key": "D",
              "text": "about"
            }
          ],
          "answer": "C",
          "explanation": ""
        },
        {
          "id": "290165",
          "kind": "mcq",
          "question": "He is jealous….. his rival’s success.",
          "options": [
            {
              "key": "A",
              "text": "by"
            },
            {
              "key": "B",
              "text": "of"
            },
            {
              "key": "C",
              "text": "with"
            },
            {
              "key": "D",
              "text": "for"
            }
          ],
          "answer": "B",
          "explanation": ""
        },
        {
          "id": "290167",
          "kind": "mcq",
          "question": "I am very opposed ………..your going abroad.",
          "options": [
            {
              "key": "A",
              "text": "to"
            },
            {
              "key": "B",
              "text": "with"
            },
            {
              "key": "C",
              "text": "by"
            },
            {
              "key": "D",
              "text": "about"
            }
          ],
          "answer": "A",
          "explanation": ""
        },
        {
          "id": "290169",
          "kind": "mcq",
          "question": "She is indifferent …….. life.",
          "options": [
            {
              "key": "A",
              "text": "with"
            },
            {
              "key": "B",
              "text": "from"
            },
            {
              "key": "C",
              "text": "about"
            },
            {
              "key": "D",
              "text": "to"
            }
          ],
          "answer": "D",
          "explanation": ""
        },
        {
          "id": "290171",
          "kind": "mcq",
          "question": "Although his last name is the same as mine, I’m not related ……. him",
          "options": [
            {
              "key": "A",
              "text": "with"
            },
            {
              "key": "B",
              "text": "to"
            },
            {
              "key": "C",
              "text": "by"
            },
            {
              "key": "D",
              "text": "for"
            }
          ],
          "answer": "B",
          "explanation": ""
        },
        {
          "id": "ET110_20",
          "kind": "mcq",
          "question": "You’ll find that this tool is very useful…………many different things.",
          "options": [
            {
              "key": "A",
              "text": "for"
            },
            {
              "key": "B",
              "text": "with"
            },
            {
              "key": "C",
              "text": "by"
            },
            {
              "key": "D",
              "text": "of"
            }
          ],
          "answer": "A",
          "explanation": ""
        },
        {
          "id": "ET110_21",
          "kind": "mcq",
          "question": "The students are very anxious ……..the results of the examination",
          "options": [
            {
              "key": "A",
              "text": "to"
            },
            {
              "key": "B",
              "text": "with"
            },
            {
              "key": "C",
              "text": "about"
            },
            {
              "key": "D",
              "text": "for"
            }
          ],
          "answer": "C",
          "explanation": ""
        },
        {
          "id": "ET110_22",
          "kind": "mcq",
          "question": "The clerk said she was tired …………hearing complaints day after day.",
          "options": [
            {
              "key": "A",
              "text": "with"
            },
            {
              "key": "B",
              "text": "of"
            },
            {
              "key": "C",
              "text": "about"
            },
            {
              "key": "D",
              "text": "for"
            }
          ],
          "answer": "B",
          "explanation": ""
        },
        {
          "id": "ET110_23",
          "kind": "mcq",
          "question": "George is still very loyal ….his friends despite their argument",
          "options": [
            {
              "key": "A",
              "text": "to"
            },
            {
              "key": "B",
              "text": "for"
            },
            {
              "key": "C",
              "text": "of"
            },
            {
              "key": "D",
              "text": "with"
            }
          ],
          "answer": "A",
          "explanation": ""
        },
        {
          "id": "ET110_24",
          "kind": "mcq",
          "question": "A good basic knowledge of English is essential……. advanced work",
          "options": [
            {
              "key": "A",
              "text": "with"
            },
            {
              "key": "B",
              "text": "by"
            },
            {
              "key": "C",
              "text": "towards"
            },
            {
              "key": "D",
              "text": "for"
            }
          ],
          "answer": "D",
          "explanation": ""
        },
        {
          "id": "ET110_25",
          "kind": "mcq",
          "question": "I think Martha was pleased …..the gift I gave her for her birthday.",
          "options": [
            {
              "key": "A",
              "text": "with"
            },
            {
              "key": "B",
              "text": "about"
            },
            {
              "key": "C",
              "text": "to"
            },
            {
              "key": "D",
              "text": "by"
            }
          ],
          "answer": "A",
          "explanation": ""
        },
        {
          "id": "ET110_26",
          "kind": "mcq",
          "question": "We’re still hopeful …………. hearing from our friends before Saturday.",
          "options": [
            {
              "key": "A",
              "text": "of"
            },
            {
              "key": "B",
              "text": "to"
            },
            {
              "key": "C",
              "text": "with"
            },
            {
              "key": "D",
              "text": "in"
            }
          ],
          "answer": "A",
          "explanation": ""
        },
        {
          "id": "ET110_27",
          "kind": "mcq",
          "question": "I’m conscious ……..their feelings, but I’m afraid ………….offending them",
          "options": [
            {
              "key": "A",
              "text": "with-of"
            },
            {
              "key": "B",
              "text": "to-of"
            },
            {
              "key": "C",
              "text": "for-to"
            },
            {
              "key": "D",
              "text": "of-of"
            }
          ],
          "answer": "D",
          "explanation": ""
        },
        {
          "id": "ET110_28",
          "kind": "mcq",
          "question": "Mr. Anderson is responsible ………hiring and firing employees.",
          "options": [
            {
              "key": "A",
              "text": "for"
            },
            {
              "key": "B",
              "text": "about"
            },
            {
              "key": "C",
              "text": "to"
            },
            {
              "key": "D",
              "text": "with"
            }
          ],
          "answer": "A",
          "explanation": ""
        },
        {
          "id": "ET110_29",
          "kind": "mcq",
          "question": "I didn’t expect to win the match. I was quite surprised…..the result.",
          "options": [
            {
              "key": "A",
              "text": "to"
            },
            {
              "key": "B",
              "text": "in"
            },
            {
              "key": "C",
              "text": "at"
            },
            {
              "key": "D",
              "text": "with"
            }
          ],
          "answer": "C",
          "explanation": ""
        },
        {
          "id": "ET110_30",
          "kind": "mcq",
          "question": "At present, my daily expenses are just about equal ………my income.",
          "options": [
            {
              "key": "A",
              "text": "for"
            },
            {
              "key": "B",
              "text": "to"
            },
            {
              "key": "C",
              "text": "with"
            },
            {
              "key": "D",
              "text": "by"
            }
          ],
          "answer": "B",
          "explanation": ""
        }
      ]
    },
    {
      "id": "PREP-C2",
      "title": "Luyện Tập Giới Từ 7 (30 câu)",
      "exercises": [
        {
          "id": "291025",
          "kind": "mcq",
          "question": "Once scientist fully understand the cause_______a disease, it becomes easier for them to find a cure for it",
          "options": [
            {
              "key": "A",
              "text": "of"
            },
            {
              "key": "B",
              "text": "by"
            },
            {
              "key": "C",
              "text": "with"
            },
            {
              "key": "D",
              "text": "to"
            }
          ],
          "answer": "A",
          "explanation": ""
        },
        {
          "id": "291026",
          "kind": "mcq",
          "question": "The children in this deprived area show a real thirst________learning",
          "options": [
            {
              "key": "A",
              "text": "for"
            },
            {
              "key": "B",
              "text": "to"
            },
            {
              "key": "C",
              "text": "of"
            },
            {
              "key": "D",
              "text": "about"
            }
          ],
          "answer": "A",
          "explanation": ""
        },
        {
          "id": "291063",
          "kind": "mcq",
          "question": "It was his contribution______molecular biology that won him the Nobel prize",
          "options": [
            {
              "key": "A",
              "text": "with"
            },
            {
              "key": "B",
              "text": "of"
            },
            {
              "key": "C",
              "text": "for"
            },
            {
              "key": "D",
              "text": "to"
            }
          ],
          "answer": "D",
          "explanation": ""
        },
        {
          "id": "291120",
          "kind": "mcq",
          "question": "I am standing here_______ my friends",
          "options": [
            {
              "key": "A",
              "text": "on account for"
            },
            {
              "key": "B",
              "text": "on behalf of"
            },
            {
              "key": "C",
              "text": "on favor of"
            },
            {
              "key": "D",
              "text": "on condition that"
            }
          ],
          "answer": "B",
          "explanation": ""
        },
        {
          "id": "291121",
          "kind": "mcq",
          "question": "_________, I had a happy childhood",
          "options": [
            {
              "key": "A",
              "text": "In the whole"
            },
            {
              "key": "B",
              "text": "On the whole"
            },
            {
              "key": "C",
              "text": "The whole of"
            },
            {
              "key": "D",
              "text": "On whole"
            }
          ],
          "answer": "B",
          "explanation": ""
        },
        {
          "id": "291122",
          "kind": "mcq",
          "question": "I can’t open this door. Have you got a key____ the other door?",
          "options": [
            {
              "key": "A",
              "text": "to"
            },
            {
              "key": "B",
              "text": "with"
            },
            {
              "key": "C",
              "text": "by"
            },
            {
              "key": "D",
              "text": "of"
            }
          ],
          "answer": "A",
          "explanation": ""
        },
        {
          "id": "291123",
          "kind": "mcq",
          "question": "I emailed Jim last week, but I still haven’t received a reply____ my message",
          "options": [
            {
              "key": "A",
              "text": "to"
            },
            {
              "key": "B",
              "text": "with"
            },
            {
              "key": "C",
              "text": "by"
            },
            {
              "key": "D",
              "text": "of"
            }
          ],
          "answer": "A",
          "explanation": ""
        },
        {
          "id": "291232",
          "kind": "mcq",
          "question": "_____ our friendly staff, you’ll find our hotel provides everything you could ever desire.",
          "options": [
            {
              "key": "A",
              "text": "In addition to"
            },
            {
              "key": "B",
              "text": "In spite of"
            },
            {
              "key": "C",
              "text": "In support of"
            },
            {
              "key": "D",
              "text": "In case of"
            }
          ],
          "answer": "A",
          "explanation": ""
        },
        {
          "id": "291233",
          "kind": "mcq",
          "question": "He is decorating the house .............. selling it",
          "options": [
            {
              "key": "A",
              "text": "with a view of"
            },
            {
              "key": "B",
              "text": "with a view to"
            },
            {
              "key": "C",
              "text": "in danger of"
            },
            {
              "key": "D",
              "text": "in danger to"
            }
          ],
          "answer": "B",
          "explanation": ""
        },
        {
          "id": "291234",
          "kind": "mcq",
          "question": "The project failed_________finiancial banking",
          "options": [
            {
              "key": "A",
              "text": "on account of"
            },
            {
              "key": "B",
              "text": "for want of"
            },
            {
              "key": "C",
              "text": "by reason of"
            },
            {
              "key": "D",
              "text": "for the purpose of"
            }
          ],
          "answer": "B",
          "explanation": ""
        },
        {
          "id": "291235",
          "kind": "mcq",
          "question": "You can’t talk to her now. She’s still_____, but I will ask her to call you back.",
          "options": [
            {
              "key": "A",
              "text": "on phone"
            },
            {
              "key": "B",
              "text": "on the phone"
            },
            {
              "key": "C",
              "text": "in the phone"
            },
            {
              "key": "D",
              "text": "in phone"
            }
          ],
          "answer": "B",
          "explanation": ""
        },
        {
          "id": "291236",
          "kind": "mcq",
          "question": "To be.....debt is to be .......danger",
          "options": [
            {
              "key": "A",
              "text": "in-out of"
            },
            {
              "key": "B",
              "text": "in-in"
            },
            {
              "key": "C",
              "text": "out of-in"
            },
            {
              "key": "D",
              "text": "out of- out of"
            }
          ],
          "answer": "B",
          "explanation": ""
        },
        {
          "id": "291237",
          "kind": "mcq",
          "question": "our style of hair maybe_______ date at present.",
          "options": [
            {
              "key": "A",
              "text": "in"
            },
            {
              "key": "B",
              "text": "on"
            },
            {
              "key": "C",
              "text": "out of"
            },
            {
              "key": "D",
              "text": "in of"
            }
          ],
          "answer": "C",
          "explanation": ""
        },
        {
          "id": "291238",
          "kind": "mcq",
          "question": "There was a rise______ the demand______ smoke alarms that week.",
          "options": [
            {
              "key": "A",
              "text": "on / on"
            },
            {
              "key": "B",
              "text": "on / of"
            },
            {
              "key": "C",
              "text": "in / for"
            },
            {
              "key": "D",
              "text": "for / in"
            }
          ],
          "answer": "C",
          "explanation": ""
        },
        {
          "id": "291239",
          "kind": "mcq",
          "question": "Donata came across the business idea______ accident!",
          "options": [
            {
              "key": "A",
              "text": "on"
            },
            {
              "key": "B",
              "text": "in"
            },
            {
              "key": "C",
              "text": "with"
            },
            {
              "key": "D",
              "text": "by"
            }
          ],
          "answer": "D",
          "explanation": ""
        },
        {
          "id": "291240",
          "kind": "mcq",
          "question": "______mistake, I took the wrong book from my desk this morning.",
          "options": [
            {
              "key": "A",
              "text": "through"
            },
            {
              "key": "B",
              "text": "by"
            },
            {
              "key": "C",
              "text": "with"
            },
            {
              "key": "D",
              "text": "in"
            }
          ],
          "answer": "B",
          "explanation": ""
        },
        {
          "id": "291241",
          "kind": "mcq",
          "question": "The main reason ...........taking the course is to improve your language skills",
          "options": [
            {
              "key": "A",
              "text": "on"
            },
            {
              "key": "B",
              "text": "of"
            },
            {
              "key": "C",
              "text": "for"
            },
            {
              "key": "D",
              "text": "with"
            }
          ],
          "answer": "C",
          "explanation": ""
        },
        {
          "id": "291242",
          "kind": "mcq",
          "question": "He noticed an increase_______ the curiosity of his neighbors after the burned cake incident.",
          "options": [
            {
              "key": "A",
              "text": "in"
            },
            {
              "key": "B",
              "text": "of"
            },
            {
              "key": "C",
              "text": "for"
            },
            {
              "key": "D",
              "text": "on"
            }
          ],
          "answer": "A",
          "explanation": ""
        },
        {
          "id": "291243",
          "kind": "mcq",
          "question": "Would you like to come______ a walk with me?",
          "options": [
            {
              "key": "A",
              "text": "with"
            },
            {
              "key": "B",
              "text": "for"
            },
            {
              "key": "C",
              "text": "in"
            },
            {
              "key": "D",
              "text": "of"
            }
          ],
          "answer": "B",
          "explanation": ""
        },
        {
          "id": "ET111_20",
          "kind": "mcq",
          "question": "Where would you like to go______holiday this year?",
          "options": [
            {
              "key": "A",
              "text": "in"
            },
            {
              "key": "B",
              "text": "on"
            },
            {
              "key": "C",
              "text": "of"
            },
            {
              "key": "D",
              "text": "from"
            }
          ],
          "answer": "B",
          "explanation": ""
        },
        {
          "id": "ET111_21",
          "kind": "mcq",
          "question": "____my opinion, he is an excellent pianist",
          "options": [
            {
              "key": "A",
              "text": "for"
            },
            {
              "key": "B",
              "text": "in"
            },
            {
              "key": "C",
              "text": "by"
            },
            {
              "key": "D",
              "text": "on"
            }
          ],
          "answer": "B",
          "explanation": ""
        },
        {
          "id": "ET111_22",
          "kind": "mcq",
          "question": "Let's drive today. I think the bus drivers are______ strike.",
          "options": [
            {
              "key": "A",
              "text": "in"
            },
            {
              "key": "B",
              "text": "on"
            },
            {
              "key": "C",
              "text": "by"
            },
            {
              "key": "D",
              "text": "for"
            }
          ],
          "answer": "B",
          "explanation": ""
        },
        {
          "id": "ET111_23",
          "kind": "mcq",
          "question": "The washing machine is............again. Let's buy a new one.",
          "options": [
            {
              "key": "A",
              "text": "out of order"
            },
            {
              "key": "B",
              "text": "out of work"
            },
            {
              "key": "C",
              "text": "out of date"
            },
            {
              "key": "D",
              "text": "out of the question"
            }
          ],
          "answer": "A",
          "explanation": ""
        },
        {
          "id": "ET111_24",
          "kind": "mcq",
          "question": "The reasons______ homelessness are many, but there is a great demand_____ a plan of action to end it.",
          "options": [
            {
              "key": "A",
              "text": "for / for"
            },
            {
              "key": "B",
              "text": "for / in"
            },
            {
              "key": "C",
              "text": "for / on"
            },
            {
              "key": "D",
              "text": "on / for"
            }
          ],
          "answer": "A",
          "explanation": ""
        },
        {
          "id": "ET111_25",
          "kind": "mcq",
          "question": "I go to cinema______times",
          "options": [
            {
              "key": "A",
              "text": "on"
            },
            {
              "key": "B",
              "text": "in"
            },
            {
              "key": "C",
              "text": "with"
            },
            {
              "key": "D",
              "text": "at"
            }
          ],
          "answer": "D",
          "explanation": ""
        },
        {
          "id": "ET111_26",
          "kind": "mcq",
          "question": "These jackets are ____ fashion",
          "options": [
            {
              "key": "A",
              "text": "on"
            },
            {
              "key": "B",
              "text": "at"
            },
            {
              "key": "C",
              "text": "out of"
            },
            {
              "key": "D",
              "text": "out"
            }
          ],
          "answer": "C",
          "explanation": ""
        },
        {
          "id": "ET111_27",
          "kind": "mcq",
          "question": "It wasn’t a bad accident. The damage _____ the car wasn’t serious",
          "options": [
            {
              "key": "A",
              "text": "to"
            },
            {
              "key": "B",
              "text": "with"
            },
            {
              "key": "C",
              "text": "of"
            },
            {
              "key": "D",
              "text": "by"
            }
          ],
          "answer": "A",
          "explanation": ""
        },
        {
          "id": "ET111_28",
          "kind": "mcq",
          "question": "She recently overcome her fear____ flying and had a holiday in South Africa",
          "options": [
            {
              "key": "A",
              "text": "of"
            },
            {
              "key": "B",
              "text": "by"
            },
            {
              "key": "C",
              "text": "with"
            },
            {
              "key": "D",
              "text": "for"
            }
          ],
          "answer": "A",
          "explanation": ""
        },
        {
          "id": "ET111_29",
          "kind": "mcq",
          "question": "She has no faith_____modern medicine.",
          "options": [
            {
              "key": "A",
              "text": "in"
            },
            {
              "key": "B",
              "text": "of"
            },
            {
              "key": "C",
              "text": "by"
            },
            {
              "key": "D",
              "text": "with"
            }
          ],
          "answer": "A",
          "explanation": ""
        },
        {
          "id": "ET111_30",
          "kind": "mcq",
          "question": "A large number________seats have been taken.",
          "options": [
            {
              "key": "A",
              "text": "of"
            },
            {
              "key": "B",
              "text": "for"
            },
            {
              "key": "C",
              "text": "with"
            },
            {
              "key": "D",
              "text": "by"
            }
          ],
          "answer": "A",
          "explanation": ""
        }
      ]
    },
    {
      "id": "PREP-C3",
      "title": "Luyện Tập Giới Từ 8 (50 câu)",
      "exercises": [
        {
          "id": "290975",
          "kind": "mcq",
          "question": "He took a photograph______ his girlfriend.",
          "options": [
            {
              "key": "A",
              "text": "on"
            },
            {
              "key": "B",
              "text": "for"
            },
            {
              "key": "C",
              "text": "of"
            },
            {
              "key": "D",
              "text": "in"
            }
          ],
          "answer": "C",
          "explanation": ""
        },
        {
          "id": "290976",
          "kind": "mcq",
          "question": "Do you have a good relationship_______ most of your relatives?",
          "options": [
            {
              "key": "A",
              "text": "with"
            },
            {
              "key": "B",
              "text": "of"
            },
            {
              "key": "C",
              "text": "in"
            },
            {
              "key": "D",
              "text": "between"
            }
          ],
          "answer": "A",
          "explanation": ""
        },
        {
          "id": "290977",
          "kind": "mcq",
          "question": "She has a great deal of experience_________ introducing new products to international markets.",
          "options": [
            {
              "key": "A",
              "text": "of"
            },
            {
              "key": "B",
              "text": "on"
            },
            {
              "key": "C",
              "text": "in"
            },
            {
              "key": "D",
              "text": "about"
            }
          ],
          "answer": "C",
          "explanation": ""
        },
        {
          "id": "290978",
          "kind": "mcq",
          "question": "His fear _____flying made travel difficult.",
          "options": [
            {
              "key": "A",
              "text": "on"
            },
            {
              "key": "B",
              "text": "of"
            },
            {
              "key": "C",
              "text": "for"
            },
            {
              "key": "D",
              "text": "in"
            }
          ],
          "answer": "B",
          "explanation": ""
        },
        {
          "id": "290979",
          "kind": "mcq",
          "question": "Did you send Alice an invitation______ the party?",
          "options": [
            {
              "key": "A",
              "text": "to"
            },
            {
              "key": "B",
              "text": "with"
            },
            {
              "key": "C",
              "text": "in"
            },
            {
              "key": "D",
              "text": "of"
            }
          ],
          "answer": "A",
          "explanation": ""
        },
        {
          "id": "290980",
          "kind": "mcq",
          "question": "His habit_____ smoking in restaurants caused many problems in California.",
          "options": [
            {
              "key": "A",
              "text": "of"
            },
            {
              "key": "B",
              "text": "on"
            },
            {
              "key": "C",
              "text": "about"
            },
            {
              "key": "D",
              "text": "with"
            }
          ],
          "answer": "A",
          "explanation": ""
        },
        {
          "id": "290981",
          "kind": "mcq",
          "question": "The company has strong links______big inventors",
          "options": [
            {
              "key": "A",
              "text": "with"
            },
            {
              "key": "B",
              "text": "for"
            },
            {
              "key": "C",
              "text": "to"
            },
            {
              "key": "D",
              "text": "from"
            }
          ],
          "answer": "A",
          "explanation": ""
        },
        {
          "id": "290982",
          "kind": "mcq",
          "question": "The search_____the missing teenager was called off",
          "options": [
            {
              "key": "A",
              "text": "on"
            },
            {
              "key": "B",
              "text": "of"
            },
            {
              "key": "C",
              "text": "for"
            },
            {
              "key": "D",
              "text": "to"
            }
          ],
          "answer": "C",
          "explanation": ""
        },
        {
          "id": "290983",
          "kind": "mcq",
          "question": "The decrease _profits is due to the bad market.",
          "options": [
            {
              "key": "A",
              "text": "on"
            },
            {
              "key": "B",
              "text": "of"
            },
            {
              "key": "C",
              "text": "in"
            },
            {
              "key": "D",
              "text": "from"
            }
          ],
          "answer": "C",
          "explanation": ""
        },
        {
          "id": "290984",
          "kind": "mcq",
          "question": "There is a real demand_____ qualified English teachers.",
          "options": [
            {
              "key": "A",
              "text": "for"
            },
            {
              "key": "B",
              "text": "of"
            },
            {
              "key": "C",
              "text": "with"
            },
            {
              "key": "D",
              "text": "on"
            }
          ],
          "answer": "A",
          "explanation": ""
        },
        {
          "id": "290985",
          "kind": "mcq",
          "question": "Who is______all these dogs? They seem to be running wild!",
          "options": [
            {
              "key": "A",
              "text": "on duty"
            },
            {
              "key": "B",
              "text": "in charge of"
            },
            {
              "key": "C",
              "text": "in authority"
            },
            {
              "key": "D",
              "text": "in duty"
            }
          ],
          "answer": "B",
          "explanation": ""
        },
        {
          "id": "290986",
          "kind": "mcq",
          "question": "We have seen a fall _ prices recently.",
          "options": [
            {
              "key": "A",
              "text": "of"
            },
            {
              "key": "B",
              "text": "for"
            },
            {
              "key": "C",
              "text": "on"
            },
            {
              "key": "D",
              "text": "in"
            }
          ],
          "answer": "D",
          "explanation": ""
        },
        {
          "id": "290987",
          "kind": "mcq",
          "question": "The cause_____ his problems is his wife.",
          "options": [
            {
              "key": "A",
              "text": "on"
            },
            {
              "key": "B",
              "text": "for"
            },
            {
              "key": "C",
              "text": "of"
            },
            {
              "key": "D",
              "text": "in"
            }
          ],
          "answer": "C",
          "explanation": ""
        },
        {
          "id": "290988",
          "kind": "mcq",
          "question": "Did you do any damage_____ the car?",
          "options": [
            {
              "key": "A",
              "text": "on"
            },
            {
              "key": "B",
              "text": "in"
            },
            {
              "key": "C",
              "text": "to"
            },
            {
              "key": "D",
              "text": "for"
            }
          ],
          "answer": "C",
          "explanation": ""
        },
        {
          "id": "290989",
          "kind": "mcq",
          "question": "I think your attitude____ your employer is very bad indeed.",
          "options": [
            {
              "key": "A",
              "text": "to"
            },
            {
              "key": "B",
              "text": "on"
            },
            {
              "key": "C",
              "text": "of"
            },
            {
              "key": "D",
              "text": "between"
            }
          ],
          "answer": "A",
          "explanation": ""
        },
        {
          "id": "290990",
          "kind": "mcq",
          "question": "She is_____ holiday now. Can you phone her at 0261.321.578.",
          "options": [
            {
              "key": "A",
              "text": "in"
            },
            {
              "key": "B",
              "text": "on"
            },
            {
              "key": "C",
              "text": "of"
            },
            {
              "key": "D",
              "text": "with"
            }
          ],
          "answer": "B",
          "explanation": ""
        },
        {
          "id": "290991",
          "kind": "mcq",
          "question": "There is a great need______ low-cost housing in this country as an answer______ the homeless problem.",
          "options": [
            {
              "key": "A",
              "text": "for / for"
            },
            {
              "key": "B",
              "text": "to / to"
            },
            {
              "key": "C",
              "text": "to / for"
            },
            {
              "key": "D",
              "text": "for / to"
            }
          ],
          "answer": "D",
          "explanation": ""
        },
        {
          "id": "290992",
          "kind": "mcq",
          "question": "His addiction_____ surfing the Internet is a problem.",
          "options": [
            {
              "key": "A",
              "text": "of"
            },
            {
              "key": "B",
              "text": "on"
            },
            {
              "key": "C",
              "text": "for"
            },
            {
              "key": "D",
              "text": "to"
            }
          ],
          "answer": "D",
          "explanation": ""
        },
        {
          "id": "290993",
          "kind": "mcq",
          "question": "Her anxiety______ speaking in public caused her to lose the job.",
          "options": [
            {
              "key": "A",
              "text": "on"
            },
            {
              "key": "B",
              "text": "of"
            },
            {
              "key": "C",
              "text": "in"
            },
            {
              "key": "D",
              "text": "about"
            }
          ],
          "answer": "D",
          "explanation": ""
        },
        {
          "id": "290994",
          "kind": "mcq",
          "question": "His belief______ god is influenced by his mother.",
          "options": [
            {
              "key": "A",
              "text": "in"
            },
            {
              "key": "B",
              "text": "of"
            },
            {
              "key": "C",
              "text": "on"
            },
            {
              "key": "D",
              "text": "for"
            }
          ],
          "answer": "A",
          "explanation": ""
        },
        {
          "id": "290995",
          "kind": "mcq",
          "question": "His dedication_______ teaching was impressive.",
          "options": [
            {
              "key": "A",
              "text": "on"
            },
            {
              "key": "B",
              "text": "in"
            },
            {
              "key": "C",
              "text": "to"
            },
            {
              "key": "D",
              "text": "of"
            }
          ],
          "answer": "C",
          "explanation": ""
        },
        {
          "id": "290996",
          "kind": "mcq",
          "question": "The delay_____ processing the visa caused problems.",
          "options": [
            {
              "key": "A",
              "text": "of"
            },
            {
              "key": "B",
              "text": "from"
            },
            {
              "key": "C",
              "text": "with"
            },
            {
              "key": "D",
              "text": "in"
            }
          ],
          "answer": "D",
          "explanation": ""
        },
        {
          "id": "290997",
          "kind": "mcq",
          "question": "______________saying the wrong thing, I chose to say nothing at all",
          "options": [
            {
              "key": "A",
              "text": "For the purpose of"
            },
            {
              "key": "B",
              "text": "For fear of"
            },
            {
              "key": "C",
              "text": "For the good of"
            },
            {
              "key": "D",
              "text": "On account of"
            }
          ],
          "answer": "B",
          "explanation": ""
        },
        {
          "id": "290998",
          "kind": "mcq",
          "question": "His fear _____flying made travel difficult.",
          "options": [
            {
              "key": "A",
              "text": "on"
            },
            {
              "key": "B",
              "text": "of"
            },
            {
              "key": "C",
              "text": "for"
            },
            {
              "key": "D",
              "text": "in"
            }
          ],
          "answer": "B",
          "explanation": ""
        },
        {
          "id": "290999",
          "kind": "mcq",
          "question": "Her fondness____ traveling led to her career in the travel industry.",
          "options": [
            {
              "key": "A",
              "text": "on"
            },
            {
              "key": "B",
              "text": "for"
            },
            {
              "key": "C",
              "text": "about"
            },
            {
              "key": "D",
              "text": "with"
            }
          ],
          "answer": "B",
          "explanation": ""
        },
        {
          "id": "291000",
          "kind": "mcq",
          "question": "His habit_____ smoking in restaurants caused many problems in California.",
          "options": [
            {
              "key": "A",
              "text": "of"
            },
            {
              "key": "B",
              "text": "on"
            },
            {
              "key": "C",
              "text": "about"
            },
            {
              "key": "D",
              "text": "with"
            }
          ],
          "answer": "A",
          "explanation": ""
        },
        {
          "id": "291001",
          "kind": "mcq",
          "question": "Her career as a pilot evolved out of her interest______ flying.",
          "options": [
            {
              "key": "A",
              "text": "on"
            },
            {
              "key": "B",
              "text": "of"
            },
            {
              "key": "C",
              "text": "with"
            },
            {
              "key": "D",
              "text": "in"
            }
          ],
          "answer": "D",
          "explanation": ""
        },
        {
          "id": "291002",
          "kind": "mcq",
          "question": "Her knowledge______ climbing helped her during the competition.",
          "options": [
            {
              "key": "A",
              "text": "in"
            },
            {
              "key": "B",
              "text": "about"
            },
            {
              "key": "C",
              "text": "of"
            },
            {
              "key": "D",
              "text": "with"
            }
          ],
          "answer": "C",
          "explanation": ""
        },
        {
          "id": "291003",
          "kind": "mcq",
          "question": "His love______ singing developed when he was a child.",
          "options": [
            {
              "key": "A",
              "text": "with"
            },
            {
              "key": "B",
              "text": "of"
            },
            {
              "key": "C",
              "text": "about"
            },
            {
              "key": "D",
              "text": "on"
            }
          ],
          "answer": "B",
          "explanation": ""
        },
        {
          "id": "291004",
          "kind": "mcq",
          "question": "Their memories_______ traveling in Africa will stay with them forever.",
          "options": [
            {
              "key": "A",
              "text": "of"
            },
            {
              "key": "B",
              "text": "on"
            },
            {
              "key": "C",
              "text": "for"
            },
            {
              "key": "D",
              "text": "with"
            }
          ],
          "answer": "A",
          "explanation": ""
        },
        {
          "id": "291005",
          "kind": "mcq",
          "question": "The process______ painting such a large mural is more complicated than you might think.",
          "options": [
            {
              "key": "A",
              "text": "in"
            },
            {
              "key": "B",
              "text": "of"
            },
            {
              "key": "C",
              "text": "about"
            },
            {
              "key": "D",
              "text": "in"
            }
          ],
          "answer": "B",
          "explanation": ""
        },
        {
          "id": "291006",
          "kind": "mcq",
          "question": "His reaction_____ winning the prize was quite funny.",
          "options": [
            {
              "key": "A",
              "text": "about"
            },
            {
              "key": "B",
              "text": "in"
            },
            {
              "key": "C",
              "text": "to"
            },
            {
              "key": "D",
              "text": "of"
            }
          ],
          "answer": "C",
          "explanation": ""
        },
        {
          "id": "291007",
          "kind": "mcq",
          "question": "We’ll send you a reply____your application letter next Monday",
          "options": [
            {
              "key": "A",
              "text": "to"
            },
            {
              "key": "B",
              "text": "for"
            },
            {
              "key": "C",
              "text": "of"
            },
            {
              "key": "D",
              "text": "about"
            }
          ],
          "answer": "A",
          "explanation": ""
        },
        {
          "id": "291008",
          "kind": "mcq",
          "question": "I’m sure we’ll find a solution______this problem",
          "options": [
            {
              "key": "A",
              "text": "with"
            },
            {
              "key": "B",
              "text": "of"
            },
            {
              "key": "C",
              "text": "to"
            },
            {
              "key": "D",
              "text": "for"
            }
          ],
          "answer": "C",
          "explanation": ""
        },
        {
          "id": "291009",
          "kind": "mcq",
          "question": "Do you have an answer_____this question?",
          "options": [
            {
              "key": "A",
              "text": "to"
            },
            {
              "key": "B",
              "text": "for"
            },
            {
              "key": "C",
              "text": "of"
            },
            {
              "key": "D",
              "text": "about"
            }
          ],
          "answer": "A",
          "explanation": ""
        },
        {
          "id": "291010",
          "kind": "mcq",
          "question": "There is clearly a difference______your car and mine",
          "options": [
            {
              "key": "A",
              "text": "from"
            },
            {
              "key": "B",
              "text": "between"
            },
            {
              "key": "C",
              "text": "among"
            },
            {
              "key": "D",
              "text": "by"
            }
          ],
          "answer": "B",
          "explanation": ""
        },
        {
          "id": "291011",
          "kind": "mcq",
          "question": "We don’t have room _____a grand piano?",
          "options": [
            {
              "key": "A",
              "text": "towards"
            },
            {
              "key": "B",
              "text": "for"
            },
            {
              "key": "C",
              "text": "with"
            },
            {
              "key": "D",
              "text": "by"
            }
          ],
          "answer": "B",
          "explanation": ""
        },
        {
          "id": "291012",
          "kind": "mcq",
          "question": "I’m against any form of cruelty_____ animals",
          "options": [
            {
              "key": "A",
              "text": "to"
            },
            {
              "key": "B",
              "text": "with"
            },
            {
              "key": "C",
              "text": "by"
            },
            {
              "key": "D",
              "text": "of"
            }
          ],
          "answer": "A",
          "explanation": ""
        },
        {
          "id": "291013",
          "kind": "mcq",
          "question": "I’m sorry; I wasn’t paying close attention ____ what you said",
          "options": [
            {
              "key": "A",
              "text": "on"
            },
            {
              "key": "B",
              "text": "at"
            },
            {
              "key": "C",
              "text": "in"
            },
            {
              "key": "D",
              "text": "to"
            }
          ],
          "answer": "D",
          "explanation": ""
        },
        {
          "id": "291014",
          "kind": "mcq",
          "question": "Don’t put much confidence_____ his words",
          "options": [
            {
              "key": "A",
              "text": "to"
            },
            {
              "key": "B",
              "text": "in"
            },
            {
              "key": "C",
              "text": "at"
            },
            {
              "key": "D",
              "text": "on"
            }
          ],
          "answer": "B",
          "explanation": ""
        },
        {
          "id": "291015",
          "kind": "mcq",
          "question": "There is no need_________a new car at the moment",
          "options": [
            {
              "key": "A",
              "text": "of"
            },
            {
              "key": "B",
              "text": "for"
            },
            {
              "key": "C",
              "text": "with"
            },
            {
              "key": "D",
              "text": "to"
            }
          ],
          "answer": "B",
          "explanation": ""
        },
        {
          "id": "291016",
          "kind": "mcq",
          "question": "Have you had any contact________Sarah?",
          "options": [
            {
              "key": "A",
              "text": "to"
            },
            {
              "key": "B",
              "text": "of"
            },
            {
              "key": "C",
              "text": "with"
            },
            {
              "key": "D",
              "text": "on"
            }
          ],
          "answer": "C",
          "explanation": ""
        },
        {
          "id": "291017",
          "kind": "mcq",
          "question": "She has great interest___________the poetry of Donne",
          "options": [
            {
              "key": "A",
              "text": "in"
            },
            {
              "key": "B",
              "text": "to"
            },
            {
              "key": "C",
              "text": "for"
            },
            {
              "key": "D",
              "text": "on"
            }
          ],
          "answer": "A",
          "explanation": ""
        },
        {
          "id": "291018",
          "kind": "mcq",
          "question": "I have no faith_______ her capabilities",
          "options": [
            {
              "key": "A",
              "text": "in"
            },
            {
              "key": "B",
              "text": "on"
            },
            {
              "key": "C",
              "text": "to"
            },
            {
              "key": "D",
              "text": "at"
            }
          ],
          "answer": "A",
          "explanation": ""
        },
        {
          "id": "291019",
          "kind": "mcq",
          "question": "In many cities the cost _____ living is pretty high.",
          "options": [
            {
              "key": "A",
              "text": "for"
            },
            {
              "key": "B",
              "text": "in"
            },
            {
              "key": "C",
              "text": "of"
            },
            {
              "key": "D",
              "text": "to"
            }
          ],
          "answer": "C",
          "explanation": ""
        },
        {
          "id": "291020",
          "kind": "mcq",
          "question": "My new job is making great demands____ my time",
          "options": [
            {
              "key": "A",
              "text": "of"
            },
            {
              "key": "B",
              "text": "in"
            },
            {
              "key": "C",
              "text": "for"
            },
            {
              "key": "D",
              "text": "on"
            }
          ],
          "answer": "D",
          "explanation": ""
        },
        {
          "id": "291021",
          "kind": "mcq",
          "question": "Jane had the idea_____starting her own business.",
          "options": [
            {
              "key": "A",
              "text": "on"
            },
            {
              "key": "B",
              "text": "of"
            },
            {
              "key": "C",
              "text": "about"
            },
            {
              "key": "D",
              "text": "for"
            }
          ],
          "answer": "B",
          "explanation": ""
        },
        {
          "id": "291022",
          "kind": "mcq",
          "question": "Workers often go on strike when their salaries don’t keep pace with increases____the cost",
          "options": [
            {
              "key": "A",
              "text": "in"
            },
            {
              "key": "B",
              "text": "with"
            },
            {
              "key": "C",
              "text": "along"
            },
            {
              "key": "D",
              "text": "to"
            }
          ],
          "answer": "A",
          "explanation": ""
        },
        {
          "id": "291023",
          "kind": "mcq",
          "question": "English is an example______a language that stresses content words within sentence",
          "options": [
            {
              "key": "A",
              "text": "for"
            },
            {
              "key": "B",
              "text": "to"
            },
            {
              "key": "C",
              "text": "on"
            },
            {
              "key": "D",
              "text": "of"
            }
          ],
          "answer": "D",
          "explanation": ""
        },
        {
          "id": "291024",
          "kind": "mcq",
          "question": "The advantage______having free time is that you can do anything you want with it",
          "options": [
            {
              "key": "A",
              "text": "of"
            },
            {
              "key": "B",
              "text": "to"
            },
            {
              "key": "C",
              "text": "about"
            },
            {
              "key": "D",
              "text": "for"
            }
          ],
          "answer": "A",
          "explanation": ""
        }
      ]
    }
  ]
}